LICENSE
README.md
setup.py
selenium_helper/__init__.py
selenium_helper/dir.py
selenium_helper/http_client.py
selenium_helper/libs.py
selenium_helper/log.py
selenium_helper/selenium_proxy.py
selenium_helper/utils.py
selenium_python_helper.egg-info/PKG-INFO
selenium_python_helper.egg-info/SOURCES.txt
selenium_python_helper.egg-info/dependency_links.txt
selenium_python_helper.egg-info/requires.txt
selenium_python_helper.egg-info/top_level.txt