Metadata-Version: 2.1
Name: selenium-python-helper
Version: 0.0.6
Summary: This is my selenium help package
Home-page: https://github.com/ckf10000/selenium-python-helper
Author: ckf10000
Author-email: ckf10000@sina.com
Classifier: Programming Language :: Python :: 3
Classifier: License :: OSI Approved :: MIT License
Classifier: Operating System :: OS Independent
License-File: LICENSE
Requires-Dist: psutil>=5.9.8
Requires-Dist: blinker==1.7.0
Requires-Dist: requests>=2.31.0
Requires-Dist: selenium>=4.21.0
Requires-Dist: pypinyin>=0.51.0
Requires-Dist: selenium-wire>=5.1.0
Requires-Dist: webdriver-manager>=4.0.1
